makefilemenu/__init__.py
makefilemenu/__main__.py
makefilemenu-0.4.5.dist-info/LICENSE
makefilemenu-0.4.5.dist-info/METADATA
makefilemenu-0.4.5.dist-info/WHEEL
makefilemenu-0.4.5.dist-info/entry_points.txt
makefilemenu-0.4.5.dist-info/top_level.txt
makefilemenu-0.4.5.dist-info/RECORD
