Metadata-Version: 2.1
Name: makefilemenu
Version: 0.4.5
Summary: Console menu for Makefiles
Home-page: https://github.com/isaacto/makefilemenu
Author: Isaac To
Author-email: isaac.to@gmail.com
Classifier: Development Status :: 4 - Beta
Classifier: Programming Language :: Python :: 3.5
Classifier: Programming Language :: Python :: 3.6
Classifier: Programming Language :: Python :: 3.7
Classifier: Programming Language :: Python :: 3.8
Classifier: Topic :: Software Development :: Libraries
Classifier: License :: OSI Approved :: MIT License
Classifier: Operating System :: POSIX :: Linux
Requires-Python: ~=3.5
License-File: LICENSE
Requires-Dist: attrs
Requires-Dist: calf
